{"keys": ["200726", "200729", "", "200210", "200198", "199692", "199650", "199182", "199194", "199122", "197693", "197283", "197281", "197271", "172572", "172557", "172560", "172532", "172535", "172537", "171996", "171999", "172003", "171947", "171950", "171954", "172023", "171361", "171364", "171368", "171422", "171417", "171321", "171324", "171328", "171406", "171409", "171281", "171284", "171288", "171381", "171385", "170779", "170667", "170670", "170674", "170733", "170737", "170740", "170637"], "data": {"170667": {"kc": 12, "oid_1": 170667, "rfor": 2, "run": 1.9, "rcoa": 0, "rorc": 1.7, "rtree": 0, "rara": 37.7, "valid": 1, "rabd": 0, "rwat": 0, "rtra": 0, "sc": 215, "rpad": 33.8, "cl6": 65, "rbuil": 22.9, "rsea": 0, "m3cd": 53404551, "cl3": 6}, "199182": {"kc": 8, "oid_1": 199182, "rfor": -99, "run": -99, "rcoa": -99, "rorc": -99, "rtree": -99, "rara": -99, "valid": 0, "rabd": -99, "rwat": -99, "rtra": -99, "sc": 209, "rpad": -99, "cl6": -99, "rbuil": -99, "rsea": -99, "m3cd": 54404489, "cl3": -99}, "172535": {"kc": 8, "oid_1": 172535, "rfor": -99, "run": -99, "rcoa": -99, "rorc": -99, "rtree": -99, "rara": -99, "valid": 0, "rabd": -99, "rwat": -99, "rtra": -99, "sc": 405, "rpad": -99, "cl6": -99, "rbuil": -99, "rsea": -99, "m3cd": 53407514, "cl3": -99}, "171947": {"kc": 8, "oid_1": 171947, "rfor": 0, "run": 0, "rcoa": 0, "rorc": 0, "rtree": 0, "rara": 0, "valid": 1, "rabd": 1.2, "rwat": 92.7, "rtra": 0, "sc": 406, "rpad": 6.1, "cl6": 65, "rbuil": 0, "rsea": 0, "m3cd": 53406521, "cl3": 6}, "172532": {"kc": 8, "oid_1": 172532, "rfor": -99, "run": -99, "rcoa": -99, "rorc": -99, "rtree": -99, "rara": -99, "valid": 0, "rabd": -99, "rwat": -99, "rtra": -99, "sc": 405, "rpad": -99, "cl6": -99, "rbuil": -99, "rsea": -99, "m3cd": 53407511, "cl3": -99}, "197283": {"kc": 8, "oid_1": 197283, "rfor": -99, "run": -99, "rcoa": -99, "rorc": -99, "rtree": -99, "rara": -99, "valid": 0, "rabd": -99, "rwat": -99, "rtra": -99, "sc": 404, "rpad": -99, "cl6": -99, "rbuil": -99, "rsea": -99, "m3cd": 54400560, "cl3": -99}, "172023": {"kc": 8, "oid_1": 172023, "rfor": -99, "run": -99, "rcoa": -99, "rorc": -99, "rtree": -99, "rara": -99, "valid": 0, "rabd": -99, "rwat": -99, "rtra": -99, "sc": 407, "rpad": -99, "cl6": -99, "rbuil": -99, "rsea": -99, "m3cd": 53406620, "cl3": -99}, "200726": {"kc": 8, "oid_1": 200726, "rfor": 57.8, "run": 2.9, "rcoa": 0, "rorc": 0, "rtree": 0, "rara": 3.9, "valid": 1, "rabd": 6, "rwat": 0, "rtra": 7.8, "sc": 202, "rpad": 0, "cl6": 47, "rbuil": 21.7, "rsea": 0, "m3cd": 54407521, "cl3": 4}, "172557": {"kc": 8, "oid_1": 172557, "rfor": 35.3, "run": 6.2, "rcoa": 0, "rorc": 0, "rtree": 1.3, "rara": 3.6, "valid": 1, "rabd": 2.7, "rwat": 0, "rtra": 0, "sc": 405, "rpad": 0, "cl6": 68, "rbuil": 50.9, "rsea": 0, "m3cd": 53407551, "cl3": 6}, "172572": {"kc": 8, "oid_1": 172572, "rfor": -99, "run": -99, "rcoa": -99, "rorc": -99, "rtree": -99, "rara": -99, "valid": 0, "rabd": -99, "rwat": -99, "rtra": -99, "sc": 405, "rpad": -99, "cl6": -99, "rbuil": -99, "rsea": -99, "m3cd": 53407583, "cl3": -99}, "200729": {"kc": 8, "oid_1": 200729, "rfor": 1.2, "run": 4.6, "rcoa": 0.5, "rorc": 0, "rtree": 0, "rara": 7.7, "valid": 1, "rabd": 3.4, "rwat": 0, "rtra": 0, "sc": 202, "rpad": 1.3, "cl6": 13, "rbuil": 15.3, "rsea": 65.9, "m3cd": 54407524, "cl3": 1}, "172003": {"kc": 8, "oid_1": 172003, "rfor": -99, "run": -99, "rcoa": -99, "rorc": -99, "rtree": -99, "rara": -99, "valid": 0, "rabd": -99, "rwat": -99, "rtra": -99, "sc": 406, "rpad": -99, "cl6": -99, "rbuil": -99, "rsea": -99, "m3cd": 53406578, "cl3": -99}, "199650": {"kc": 8, "oid_1": 199650, "rfor": -99, "run": -99, "rcoa": -99, "rorc": -99, "rtree": -99, "rara": -99, "valid": 0, "rabd": -99, "rwat": -99, "rtra": -99, "sc": 341, "rpad": -99, "cl6": -99, "rbuil": -99, "rsea": -99, "m3cd": 54405459, "cl3": -99}, "171328": {"kc": 12, "oid_1": 171328, "rfor": 1.9, "run": 0, "rcoa": 0, "rorc": 0, "rtree": 0, "rara": 2, "valid": 1, "rabd": 0, "rwat": 62.1, "rtra": 0, "sc": 202, "rpad": 26.5, "cl6": 65, "rbuil": 7.3, "rsea": 0, "m3cd": 53405548, "cl3": 6}, "170779": {"kc": 8, "oid_1": 170779, "rfor": -99, "run": -99, "rcoa": -99, "rorc": -99, "rtree": -99, "rara": -99, "valid": 0, "rabd": -99, "rwat": -99, "rtra": -99, "sc": 407, "rpad": -99, "cl6": -99, "rbuil": -99, "rsea": -99, "m3cd": 53404697, "cl3": -99}, "171324": {"kc": 12, "oid_1": 171324, "rfor": 17.2, "run": 0.5, "rcoa": 0, "rorc": 0, "rtree": 0, "rara": 26.7, "valid": 1, "rabd": 0, "rwat": 0, "rtra": 0, "sc": 349, "rpad": 28.4, "cl6": 65, "rbuil": 27.2, "rsea": 0, "m3cd": 53405544, "cl3": 6}, "171321": {"kc": 12, "oid_1": 171321, "rfor": 40.8, "run": 1.5, "rcoa": 0, "rorc": 0.2, "rtree": 0, "rara": 13.2, "valid": 1, "rabd": 0, "rwat": 0, "rtra": 0, "sc": 349, "rpad": 35.3, "cl6": 65, "rbuil": 8.9, "rsea": 0, "m3cd": 53405541, "cl3": 6}, "171368": {"kc": 8, "oid_1": 171368, "rfor": 14.5, "run": 5.8, "rcoa": 0, "rorc": 0, "rtree": 0, "rara": 27.9, "valid": 1, "rabd": 11, "rwat": 7.1, "rtra": 3.4, "sc": 407, "rpad": 14.7, "cl6": 65, "rbuil": 15.6, "rsea": 0, "m3cd": 53405588, "cl3": 6}, "200210": {"kc": 8, "oid_1": 200210, "rfor": 6.6, "run": 12.7, "rcoa": 0, "rorc": 0, "rtree": 0, "rara": 7, "valid": 1, "rabd": 3.2, "rwat": 5.9, "rtra": 0, "sc": 202, "rpad": 0, "cl6": 68, "rbuil": 64.5, "rsea": 0, "m3cd": 54406581, "cl3": 6}, "171281": {"kc": 12, "oid_1": 171281, "rfor": 0, "run": 0, "rcoa": 0, "rorc": 0, "rtree": 0, "rara": 12.3, "valid": 1, "rabd": 0, "rwat": 4.5, "rtra": 0, "sc": 348, "rpad": 72.8, "cl6": 65, "rbuil": 10.3, "rsea": 0, "m3cd": 53405501, "cl3": 6}, "171409": {"kc": 8, "oid_1": 171409, "rfor": -99, "run": -99, "rcoa": -99, "rorc": -99, "rtree": -99, "rara": -99, "valid": 0, "rabd": -99, "rwat": -99, "rtra": -99, "sc": 407, "rpad": -99, "cl6": -99, "rbuil": -99, "rsea": -99, "m3cd": 53405644, "cl3": -99}, "171284": {"kc": 12, "oid_1": 171284, "rfor": 0, "run": 0, "rcoa": 0, "rorc": 0, "rtree": 0, "rara": 1.2, "valid": 1, "rabd": 0, "rwat": 0, "rtra": 0, "sc": 361, "rpad": 92.8, "cl6": 65, "rbuil": 6.1, "rsea": 0, "m3cd": 53405504, "cl3": 6}, "171361": {"kc": 12, "oid_1": 171361, "rfor": 35.8, "run": 0, "rcoa": 0, "rorc": 0, "rtree": 2.5, "rara": 22.6, "valid": 1, "rabd": 0, "rwat": 0.8, "rtra": 0, "sc": 344, "rpad": 32.2, "cl6": 65, "rbuil": 6.1, "rsea": 0, "m3cd": 53405581, "cl3": 6}, "171288": {"kc": 12, "oid_1": 171288, "rfor": 50.5, "run": 0.1, "rcoa": 0, "rorc": 0, "rtree": 0, "rara": 39.3, "valid": 1, "rabd": 0.1, "rwat": 0, "rtra": 0, "sc": 202, "rpad": 7.6, "cl6": 46, "rbuil": 2.4, "rsea": 0, "m3cd": 53405508, "cl3": 4}, "171364": {"kc": 12, "oid_1": 171364, "rfor": 6.4, "run": 0.4, "rcoa": 0, "rorc": 0, "rtree": 0, "rara": 4.8, "valid": 1, "rabd": 2.5, "rwat": 0, "rtra": 0, "sc": 349, "rpad": 70.2, "cl6": 65, "rbuil": 15.8, "rsea": 0, "m3cd": 53405584, "cl3": 6}, "197281": {"kc": 8, "oid_1": 197281, "rfor": -99, "run": -99, "rcoa": -99, "rorc": -99, "rtree": -99, "rara": -99, "valid": 0, "rabd": -99, "rwat": -99, "rtra": -99, "sc": 404, "rpad": -99, "cl6": -99, "rbuil": -99, "rsea": -99, "m3cd": 54400541, "cl3": -99}, "170737": {"kc": 12, "oid_1": 170737, "rfor": 24.5, "run": 0.5, "rcoa": 0, "rorc": 0.1, "rtree": 0, "rara": 15.2, "valid": 1, "rabd": 7.8, "rwat": 0, "rtra": 0, "sc": 202, "rpad": 19.1, "cl6": 65, "rbuil": 17.3, "rsea": 15.5, "m3cd": 53404655, "cl3": 6}, "170674": {"kc": 12, "oid_1": 170674, "rfor": 24, "run": 0, "rcoa": 0, "rorc": 0, "rtree": 0, "rara": 36.9, "valid": 1, "rabd": 0, "rwat": 0, "rtra": 0, "sc": 362, "rpad": 20.9, "cl6": 46, "rbuil": 18.2, "rsea": 0, "m3cd": 53404558, "cl3": 4}, "171950": {"kc": 8, "oid_1": 171950, "rfor": 0, "run": 0, "rcoa": 0, "rorc": 0, "rtree": 0, "rara": 0, "valid": 1, "rabd": 0, "rwat": 29.5, "rtra": 0, "sc": 406, "rpad": 70.5, "cl6": 65, "rbuil": 0, "rsea": 0, "m3cd": 53406524, "cl3": 6}, "199692": {"kc": 8, "oid_1": 199692, "rfor": 1.2, "run": 24.2, "rcoa": 0, "rorc": 0, "rtree": 0, "rara": 0, "valid": 1, "rabd": 0, "rwat": 0.3, "rtra": 2.7, "sc": 202, "rpad": 0, "cl6": 13, "rbuil": 14.7, "rsea": 56.9, "m3cd": 54405590, "cl3": 1}, "170670": {"kc": 12, "oid_1": 170670, "rfor": 3.4, "run": 0.1, "rcoa": 0, "rorc": 0, "rtree": 0, "rara": 39.7, "valid": 1, "rabd": 0, "rwat": 3.6, "rtra": 0.5, "sc": 215, "rpad": 46.1, "cl6": 65, "rbuil": 6.6, "rsea": 0, "m3cd": 53404554, "cl3": 6}, "172560": {"kc": 8, "oid_1": 172560, "rfor": -99, "run": -99, "rcoa": -99, "rorc": -99, "rtree": -99, "rara": -99, "valid": 0, "rabd": -99, "rwat": -99, "rtra": -99, "sc": 405, "rpad": -99, "cl6": -99, "rbuil": -99, "rsea": -99, "m3cd": 53407554, "cl3": -99}, "171381": {"kc": 12, "oid_1": 171381, "rfor": 3.1, "run": 0.9, "rcoa": 1, "rorc": 0, "rtree": 0, "rara": 6.6, "valid": 1, "rabd": 0, "rwat": 0.1, "rtra": 0, "sc": 202, "rpad": 74.3, "cl6": 65, "rbuil": 14, "rsea": 0, "m3cd": 53405601, "cl3": 6}, "199194": {"kc": 8, "oid_1": 199194, "rfor": 4.8, "run": 2.4, "rcoa": 1.4, "rorc": 0, "rtree": 0, "rara": 4.7, "valid": 1, "rabd": 1.2, "rwat": 0, "rtra": 0, "sc": 209, "rpad": 0, "cl6": 13, "rbuil": 10.8, "rsea": 74.7, "m3cd": 54404550, "cl3": 1}, "170637": {"kc": 12, "oid_1": 170637, "rfor": 19.4, "run": 0.3, "rcoa": 12.1, "rorc": 0.1, "rtree": 0, "rara": 22.7, "valid": 1, "rabd": 0, "rwat": 0.4, "rtra": 0, "sc": 215, "rpad": 4.5, "cl6": 65, "rbuil": 9.5, "rsea": 31, "m3cd": 53404511, "cl3": 6}, "171385": {"kc": 8, "oid_1": 171385, "rfor": 12.2, "run": 3.1, "rcoa": 1, "rorc": 0.4, "rtree": 0.7, "rara": 48.1, "valid": 1, "rabd": 4.3, "rwat": 0, "rtra": 0, "sc": 407, "rpad": 10, "cl6": 65, "rbuil": 20.2, "rsea": 0, "m3cd": 53405605, "cl3": 6}, "197693": {"kc": 8, "oid_1": 197693, "rfor": -99, "run": -99, "rcoa": -99, "rorc": -99, "rtree": -99, "rara": -99, "valid": 0, "rabd": -99, "rwat": -99, "rtra": -99, "sc": 403, "rpad": -99, "cl6": -99, "rbuil": -99, "rsea": -99, "m3cd": 54401409, "cl3": -99}, "197271": {"kc": 8, "oid_1": 197271, "rfor": 20, "run": 1.8, "rcoa": 0, "rorc": 0, "rtree": 0.3, "rara": 43.7, "valid": 1, "rabd": 8.6, "rwat": 0, "rtra": 0, "sc": 405, "rpad": 21.2, "cl6": 68, "rbuil": 4.5, "rsea": 0, "m3cd": 54400501, "cl3": 6}, "171954": {"kc": 8, "oid_1": 171954, "rfor": 5, "run": 81.7, "rcoa": 0, "rorc": 0, "rtree": 0, "rara": 0.1, "valid": 1, "rabd": 0.9, "rwat": 0, "rtra": 4.6, "sc": 407, "rpad": 0.2, "cl6": 65, "rbuil": 7.6, "rsea": 0, "m3cd": 53406528, "cl3": 6}, "171422": {"kc": 8, "oid_1": 171422, "rfor": 17.7, "run": 5.6, "rcoa": 3.9, "rorc": 0, "rtree": 0, "rara": 34.7, "valid": 1, "rabd": 4.3, "rwat": 0, "rtra": 0, "sc": 407, "rpad": 24.4, "cl6": 65, "rbuil": 9.2, "rsea": 0.2, "m3cd": 53405681, "cl3": 6}, "170740": {"kc": 12, "oid_1": 170740, "rfor": 3.3, "run": 0.3, "rcoa": 0, "rorc": 0, "rtree": 0, "rara": 34.8, "valid": 1, "rabd": 0, "rwat": 0.2, "rtra": 0, "sc": 202, "rpad": 36.7, "cl6": 65, "rbuil": 24.7, "rsea": 0, "m3cd": 53404658, "cl3": 6}, "171406": {"kc": 8, "oid_1": 171406, "rfor": 3.5, "run": 16.2, "rcoa": 0, "rorc": 0, "rtree": 0, "rara": 23.7, "valid": 1, "rabd": 3, "rwat": 0, "rtra": 3.6, "sc": 407, "rpad": 36.6, "cl6": 65, "rbuil": 13.3, "rsea": 0, "m3cd": 53405641, "cl3": 6}, "171999": {"kc": 8, "oid_1": 171999, "rfor": -99, "run": -99, "rcoa": -99, "rorc": -99, "rtree": -99, "rara": -99, "valid": 0, "rabd": -99, "rwat": -99, "rtra": -99, "sc": 406, "rpad": -99, "cl6": -99, "rbuil": -99, "rsea": -99, "m3cd": 53406574, "cl3": -99}, "171996": {"kc": 8, "oid_1": 171996, "rfor": 12.5, "run": 24.4, "rcoa": 0, "rorc": 0.1, "rtree": 0.9, "rara": 7, "valid": 1, "rabd": 0, "rwat": 0, "rtra": 7, "sc": 406, "rpad": 0.6, "cl6": 65, "rbuil": 47.7, "rsea": 0, "m3cd": 53406571, "cl3": 6}, "200198": {"kc": 8, "oid_1": 200198, "rfor": -99, "run": -99, "rcoa": -99, "rorc": -99, "rtree": -99, "rara": -99, "valid": 0, "rabd": -99, "rwat": -99, "rtra": -99, "sc": 202, "rpad": -99, "cl6": -99, "rbuil": -99, "rsea": -99, "m3cd": 54406531, "cl3": -99}, "199122": {"kc": 8, "oid_1": 199122, "rfor": 3.3, "run": 3.3, "rcoa": 1.9, "rorc": 0, "rtree": 0, "rara": 8.8, "valid": 1, "rabd": 0.6, "rwat": 0, "rtra": 0, "sc": 209, "rpad": 2.8, "cl6": 68, "rbuil": 30.8, "rsea": 48.5, "m3cd": 54404429, "cl3": 6}, "172537": {"kc": 8, "oid_1": 172537, "rfor": -99, "run": -99, "rcoa": -99, "rorc": -99, "rtree": -99, "rara": -99, "valid": 0, "rabd": -99, "rwat": -99, "rtra": -99, "sc": 405, "rpad": -99, "cl6": -99, "rbuil": -99, "rsea": -99, "m3cd": 53407516, "cl3": -99}, "171417": {"kc": 8, "oid_1": 171417, "rfor": -99, "run": -99, "rcoa": -99, "rorc": -99, "rtree": -99, "rara": -99, "valid": 0, "rabd": -99, "rwat": -99, "rtra": -99, "sc": 407, "rpad": -99, "cl6": -99, "rbuil": -99, "rsea": -99, "m3cd": 53405663, "cl3": -99}, "170733": {"kc": 12, "oid_1": 170733, "rfor": 15.6, "run": 0.5, "rcoa": 0, "rorc": 0, "rtree": 0, "rara": 57.2, "valid": 1, "rabd": 0.4, "rwat": 0, "rtra": 0, "sc": 202, "rpad": 10.7, "cl6": 82, "rbuil": 15.7, "rsea": 0, "m3cd": 53404651, "cl3": 8}}, "grid": [" !##############################################################", "$###############################################################", "%###############################################################", "&###############################################################", "'###############################################################", "(###############################################################", ")###############################################################", "*###############################################################", "################################################################", "################################################################", "################################################################", "################################################################", "################################################################", "################################################################", "+###############################################################", ",###############################################################", "-###############################################################", "./##############################################################", "01##############################################################", "234#############################################################", "567#############################################################", "89:;############################################################", "<=>?@###########################################################", "ABCDE###########################################################", "FGHIJK##########################################################", "LMNOPQ##########################################################", "R###############################################################", "################################################################", "################################################################", "################################################################", "################################################################", "################################################################", "################################################################", "################################################################", "################################################################", "################################################################", "################################################################", "################################################################", "################################################################", "################################################################", "################################################################", "################################################################", "################################################################", "################################################################", "################################################################", "################################################################", "################################################################", "################################################################", "################################################################", "################################################################", "################################################################", "################################################################", "################################################################", "################################################################", "################################################################", "################################################################", "################################################################", "################################################################", "################################################################", "################################################################", "################################################################", "################################################################", "################################################################", "################################################################"]}